{"devicePlatform":"","logFolder":"C:\\Users\\AV2017005903\\Documents\\apollo-automation\\Reports\\Story 41\\20180315_123943","runData":{"hostName":"AV2017005903 - NBMP18A211ITSQA.corp.bankbtpn.co.id","os":"Windows 10 64bit","katalonVersion":"5.0.0.1","deviceOS":"Android","appiumVersion":"1.6.5","deviceModel":"ASUS_X014D","hostAddress":"192.168.17.167","deviceManufacturer":"asus","deviceId":"GBAXGV411465ERX","deviceName":"asus ASUS_X014D 5.1.1","deviceOSVersion":"5.1.1"},"type":"TEST_SUITE","name":"Story 41","id":"Test Suites/Story 41","source":"","message":"Test Cases/Story 41 - Create Expense/TC 8 FAILED because (of) Failed to tap on element \u0027Object Repository/Sidebar Menu/Operasional/Pengeluaran/10 Maret 2018\u0027 (Root cause: Object Object Repository/Sidebar Menu/Operasional/Pengeluaran/10 Maret 2018 not found)","description":"","startTime":1521092385076,"endTime":1521092552896,"childRecords":[{"isOptional":false,"type":"TEST_CASE","name":"Test Cases/Story 41 - Create Expense/TC 1","id":"Test Cases/Story 41 - Create Expense/TC 1","source":"C:\\\\Users\\\\AV2017005903\\\\Documents\\\\apollo-automationTest Cases\\\\Story 41 - Create Expense\\\\TC 1.tc","message":"Test Cases/Story 41 - Create Expense/TC 1","description":"Create Expense - View","startTime":1521092385436,"endTime":1521092430055,"childRecords":[{"testStatus":{"stackTrace":"","statusValue":"INFO"},"type":"MESSAGE","name":"","message":"Evaluating variables for test case","startTime":1521092385626,"endTime":0,"childRecords":[],"interuppted":false},{"index":1,"isIgnoredIfFailed":false,"type":"TEST_STEP","name":"comment","message":"Start Story 41","description":"","startTime":1521092386097,"endTime":1521092386151,"childRecords":[],"interuppted":false},{"index":2,"isIgnoredIfFailed":false,"type":"TEST_STEP","name":"Statement - apkPath \u003d com.kms.katalon.core.util.internal.PathUtil.relativeToAbsolutePath(apkName, com.kms.katalon.core.configuration.RunConfiguration.getProjectDir())","description":"Step 1 - [Melakukan Kelola Stock]","startTime":1521092386151,"endTime":1521092386162,"childRecords":[],"interuppted":false},{"index":3,"isIgnoredIfFailed":false,"type":"TEST_STEP","name":"startApplication","message":"Started app at: \u0027C:\\Users\\AV2017005903\\Documents\\apollo-automation\\13 Maret 17.23.apk\u0027","description":"","startTime":1521092386164,"endTime":1521092402266,"childRecords":[{"testStatus":{"stackTrace":"","statusValue":"PASSED"},"type":"MESSAGE","name":"","message":"Started app at: \u0027C:\\Users\\AV2017005903\\Documents\\apollo-automation\\13 Maret 17.23.apk\u0027","startTime":1521092402266,"endTime":0,"childRecords":[],"interuppted":false}],"interuppted":false},{"index":4,"isIgnoredIfFailed":false,"type":"TEST_STEP","name":"tap","message":"Tapped on element \u0027Object Repository/Login/Daftar Sekarang - Belum Punya Akun\u0027","description":"Mengklik \\\"Daftar Sekarang\\\" untuk masuk ke halaman Home/Beranda","startTime":1521092402266,"endTime":1521092409253,"childRecords":[{"testStatus":{"stackTrace":"","statusValue":"PASSED"},"type":"MESSAGE","name":"","message":"Tapped on element \u0027Object Repository/Login/Daftar Sekarang - Belum Punya Akun\u0027","startTime":1521092409253,"endTime":0,"childRecords":[],"interuppted":false}],"interuppted":false},{"index":5,"isIgnoredIfFailed":false,"type":"TEST_STEP","name":"waitForElementPresent","message":"Element \u0027Object Repository/Sidebar Menu/HamburgerButton\u0027 is present","description":"Menunggu hingga button sebelum Humburger button di klik","startTime":1521092409254,"endTime":1521092413111,"childRecords":[{"testStatus":{"stackTrace":"","statusValue":"PASSED"},"type":"MESSAGE","name":"","message":"Element \u0027Object Repository/Sidebar Menu/HamburgerButton\u0027 is present","startTime":1521092413109,"endTime":0,"childRecords":[],"interuppted":false}],"interuppted":false},{"index":6,"isIgnoredIfFailed":false,"type":"TEST_STEP","name":"tap","message":"Tapped on element \u0027Object Repository/Sidebar Menu/HamburgerButton\u0027","description":"Mengklik Hamburger Button kemdian memilih Operasional untuk masuk ke halaman Kasir, Stock, Pengeluaran dan Rincian","startTime":1521092413112,"endTime":1521092414419,"childRecords":[{"testStatus":{"stackTrace":"","statusValue":"PASSED"},"type":"MESSAGE","name":"","message":"Tapped on element \u0027Object Repository/Sidebar Menu/HamburgerButton\u0027","startTime":1521092414417,"endTime":0,"childRecords":[],"interuppted":false}],"interuppted":false},{"index":7,"isIgnoredIfFailed":false,"type":"TEST_STEP","name":"tap","message":"Tapped on element \u0027Object Repository/Sidebar Menu/Operasional/Operasional - Sidebar Menu\u0027","description":"Mengklik \\\"Operasional\\\" untuk bisa direct ke screen Stock","startTime":1521092414420,"endTime":1521092416046,"childRecords":[{"testStatus":{"stackTrace":"","statusValue":"PASSED"},"type":"MESSAGE","name":"","message":"Tapped on element \u0027Object Repository/Sidebar Menu/Operasional/Operasional - Sidebar Menu\u0027","startTime":1521092416040,"endTime":0,"childRecords":[],"interuppted":false}],"interuppted":false},{"index":8,"isIgnoredIfFailed":false,"type":"TEST_STEP","name":"tap","message":"Tapped on element \u0027Object Repository/Sidebar Menu/Operasional/Pengeluaran/PengeluaranNavbar\u0027","description":"Click Navbar \u0027Pengeluaran\u0027","startTime":1521092416048,"endTime":1521092419004,"childRecords":[{"testStatus":{"stackTrace":"","statusValue":"PASSED"},"type":"MESSAGE","name":"","message":"Tapped on element \u0027Object Repository/Sidebar Menu/Operasional/Pengeluaran/PengeluaranNavbar\u0027","startTime":1521092419002,"endTime":0,"childRecords":[],"interuppted":false}],"interuppted":false},{"index":9,"isIgnoredIfFailed":false,"type":"TEST_STEP","name":"delay","message":"Delayed 5 second(s)","description":"","startTime":1521092419005,"endTime":1521092424043,"childRecords":[{"testStatus":{"stackTrace":"","statusValue":"PASSED"},"type":"MESSAGE","name":"","message":"Delayed 5 second(s)","startTime":1521092424041,"endTime":0,"childRecords":[],"interuppted":false}],"interuppted":false},{"index":10,"isIgnoredIfFailed":false,"type":"TEST_STEP","name":"waitForElementPresent","message":"Element \u0027Object Repository/Sidebar Menu/Operasional/Pengeluaran/TAMBAH CATATAN - Button\u0027 is present","description":"Menungg//////////////////////u hingga elemen Pengeluaran barang untuk melanjutkan action element \\\"Tambah Catatan\\\"","startTime":1521092424043,"endTime":1521092424348,"childRecords":[{"testStatus":{"stackTrace":"","statusValue":"PASSED"},"type":"MESSAGE","name":"","message":"Element \u0027Object Repository/Sidebar Menu/Operasional/Pengeluaran/TAMBAH CATATAN - Button\u0027 is present","startTime":1521092424346,"endTime":0,"childRecords":[],"interuppted":false}],"interuppted":false},{"index":11,"isIgnoredIfFailed":false,"type":"TEST_STEP","name":"tap","message":"Tapped on element \u0027Object Repository/Sidebar Menu/Operasional/Pengeluaran/TAMBAH CATATAN - Button\u0027","description":"Mengklik Button \\\"Tambah Catatan\\\"","startTime":1521092424350,"endTime":1521092425046,"childRecords":[{"testStatus":{"stackTrace":"","statusValue":"PASSED"},"type":"MESSAGE","name":"","message":"Tapped on element \u0027Object Repository/Sidebar Menu/Operasional/Pengeluaran/TAMBAH CATATAN - Button\u0027","startTime":1521092425043,"endTime":0,"childRecords":[],"interuppted":false}],"interuppted":false},{"index":12,"isIgnoredIfFailed":false,"type":"TEST_STEP","name":"delay","message":"Delayed 5 second(s)","description":"","startTime":1521092425046,"endTime":1521092430054,"childRecords":[{"testStatus":{"stackTrace":"","statusValue":"PASSED"},"type":"MESSAGE","name":"","message":"Delayed 5 second(s)","startTime":1521092430053,"endTime":0,"childRecords":[],"interuppted":false}],"interuppted":false},{"testStatus":{"stackTrace":"","statusValue":"PASSED"},"type":"MESSAGE","name":"","message":"Test Cases/Story 41 - Create Expense/TC 1","startTime":1521092430054,"endTime":0,"childRecords":[],"interuppted":false}],"interuppted":false},{"isOptional":false,"type":"TEST_CASE","name":"Test Cases/Story 41 - Create Expense/TC 2","id":"Test Cases/Story 41 - Create Expense/TC 2","source":"C:\\\\Users\\\\AV2017005903\\\\Documents\\\\apollo-automationTest Cases\\\\Story 41 - Create Expense\\\\TC 2.tc","message":"Test Cases/Story 41 - Create Expense/TC 2","description":"Create Expense - Title","startTime":1521092430109,"endTime":1521092452413,"childRecords":[{"testStatus":{"stackTrace":"","statusValue":"INFO"},"type":"MESSAGE","name":"","message":"Evaluating variables for test case","startTime":1521092430111,"endTime":0,"childRecords":[],"interuppted":false},{"index":1,"isIgnoredIfFailed":false,"type":"TEST_STEP","name":"tap","message":"Tapped on element \u0027Object Repository/Sidebar Menu/Operasional/Pengeluaran/Judul Catatan - TextBox\u0027","description":"","startTime":1521092430261,"endTime":1521092430677,"childRecords":[{"testStatus":{"stackTrace":"","statusValue":"PASSED"},"type":"MESSAGE","name":"","message":"Tapped on element \u0027Object Repository/Sidebar Menu/Operasional/Pengeluaran/Judul Catatan - TextBox\u0027","startTime":1521092430674,"endTime":0,"childRecords":[],"interuppted":false}],"interuppted":false},{"index":2,"isIgnoredIfFailed":false,"type":"TEST_STEP","name":"setText","message":"Text \u0027Pengeluaran Kos Kosan\u0027 has been set to element \u0027Object Repository/Sidebar Menu/Operasional/Pengeluaran/Judul Catatan - TextBox\u0027","description":"Mengklik TextBox Judul MengInput Text pada Judul Catatan","startTime":1521092430677,"endTime":1521092446103,"childRecords":[{"testStatus":{"stackTrace":"","statusValue":"PASSED"},"type":"MESSAGE","name":"","message":"Text \u0027Pengeluaran Kos Kosan\u0027 has been set to element \u0027Object Repository/Sidebar Menu/Operasional/Pengeluaran/Judul Catatan - TextBox\u0027","startTime":1521092446100,"endTime":0,"childRecords":[],"interuppted":false}],"interuppted":false},{"index":3,"isIgnoredIfFailed":false,"type":"TEST_STEP","name":"verifyElementText","message":"Actual text and expected text of test object \u0027Object Repository/Sidebar Menu/Operasional/Pengeluaran/Judul Catatan - TextBox\u0027 are matched.","description":"","startTime":1521092446104,"endTime":1521092447078,"childRecords":[{"testStatus":{"stackTrace":"","statusValue":"PASSED"},"type":"MESSAGE","name":"","message":"Actual text and expected text of test object \u0027Object Repository/Sidebar Menu/Operasional/Pengeluaran/Judul Catatan - TextBox\u0027 are matched.","startTime":1521092447076,"endTime":0,"childRecords":[],"interuppted":false}],"interuppted":false},{"index":4,"isIgnoredIfFailed":false,"type":"TEST_STEP","name":"getText","message":"Text of element \u0027Object Repository/Sidebar Menu/Operasional/Pengeluaran/Judul Catatan - TextBox\u0027 is: \u0027Pengeluaran Kos Kosan\u0027","description":"","startTime":1521092447082,"endTime":1521092447385,"childRecords":[{"testStatus":{"stackTrace":"","statusValue":"PASSED"},"type":"MESSAGE","name":"","message":"Text of element \u0027Object Repository/Sidebar Menu/Operasional/Pengeluaran/Judul Catatan - TextBox\u0027 is: \u0027Pengeluaran Kos Kosan\u0027","startTime":1521092447383,"endTime":0,"childRecords":[],"interuppted":false}],"interuppted":false},{"index":5,"isIgnoredIfFailed":false,"type":"TEST_STEP","name":"hideKeyboard","message":"Keyboard is hidden","description":"Keyboard device tertutup","startTime":1521092447386,"endTime":1521092448196,"childRecords":[{"testStatus":{"stackTrace":"","statusValue":"PASSED"},"type":"MESSAGE","name":"","message":"Keyboard is hidden","startTime":1521092448080,"endTime":0,"childRecords":[],"interuppted":false}],"interuppted":false},{"index":6,"isIgnoredIfFailed":false,"type":"TEST_STEP","name":"tap","message":"Tapped on element \u0027Object Repository/Sidebar Menu/Operasional/Pengeluaran/Simpan - Tambah Catatan\u0027","description":"","startTime":1521092448196,"endTime":1521092449406,"childRecords":[{"testStatus":{"stackTrace":"","statusValue":"PASSED"},"type":"MESSAGE","name":"","message":"Tapped on element \u0027Object Repository/Sidebar Menu/Operasional/Pengeluaran/Simpan - Tambah Catatan\u0027","startTime":1521092449405,"endTime":0,"childRecords":[],"interuppted":false}],"interuppted":false},{"index":7,"isIgnoredIfFailed":false,"type":"TEST_STEP","name":"delay","message":"Delayed 3 second(s)","description":"","startTime":1521092449407,"endTime":1521092452412,"childRecords":[{"testStatus":{"stackTrace":"","statusValue":"PASSED"},"type":"MESSAGE","name":"","message":"Delayed 3 second(s)","startTime":1521092452411,"endTime":0,"childRecords":[],"interuppted":false}],"interuppted":false},{"testStatus":{"stackTrace":"","statusValue":"PASSED"},"type":"MESSAGE","name":"","message":"Test Cases/Story 41 - Create Expense/TC 2","startTime":1521092452413,"endTime":0,"childRecords":[],"interuppted":false}],"interuppted":false},{"isOptional":false,"type":"TEST_CASE","name":"Test Cases/Story 41 - Create Expense/TC 3","id":"Test Cases/Story 41 - Create Expense/TC 3","source":"C:\\\\Users\\\\AV2017005903\\\\Documents\\\\apollo-automationTest Cases\\\\Story 41 - Create Expense\\\\TC 3.tc","message":"Test Cases/Story 41 - Create Expense/TC 3","description":"Create Expense - Pilih Kategori","startTime":1521092452473,"endTime":1521092460382,"childRecords":[{"testStatus":{"stackTrace":"","statusValue":"INFO"},"type":"MESSAGE","name":"","message":"Evaluating variables for test case","startTime":1521092452505,"endTime":0,"childRecords":[],"interuppted":false},{"index":1,"isIgnoredIfFailed":false,"type":"TEST_STEP","name":"clearText","message":"Element \u0027Object Repository/Sidebar Menu/Operasional/Pengeluaran/Judul Catatan - TextBox\u0027 text is cleared","description":"","startTime":1521092452625,"endTime":1521092454735,"childRecords":[{"testStatus":{"stackTrace":"","statusValue":"PASSED"},"type":"MESSAGE","name":"","message":"Element \u0027Object Repository/Sidebar Menu/Operasional/Pengeluaran/Judul Catatan - TextBox\u0027 text is cleared","startTime":1521092454734,"endTime":0,"childRecords":[],"interuppted":false}],"interuppted":false},{"index":2,"isIgnoredIfFailed":false,"type":"TEST_STEP","name":"waitForElementPresent","message":"Element \u0027Object Repository/Sidebar Menu/Operasional/Pengeluaran/Pilih Kategori 1\u0027 is present","description":"Menunggu hingga elemen Input Judul Catatan selesai untuk melanjutkan action element \\\"Tambah Catatan\\\"","startTime":1521092454736,"endTime":1521092455698,"childRecords":[{"testStatus":{"stackTrace":"","statusValue":"PASSED"},"type":"MESSAGE","name":"","message":"Element \u0027Object Repository/Sidebar Menu/Operasional/Pengeluaran/Pilih Kategori 1\u0027 is present","startTime":1521092455695,"endTime":0,"childRecords":[],"interuppted":false}],"interuppted":false},{"index":3,"isIgnoredIfFailed":false,"type":"TEST_STEP","name":"tap","message":"Tapped on element \u0027Object Repository/Sidebar Menu/Operasional/Pengeluaran/Pilih Kategori 1\u0027","description":"Mengklik \\\"Pilih Kategori\\\"","startTime":1521092455698,"endTime":1521092456225,"childRecords":[{"testStatus":{"stackTrace":"","statusValue":"PASSED"},"type":"MESSAGE","name":"","message":"Tapped on element \u0027Object Repository/Sidebar Menu/Operasional/Pengeluaran/Pilih Kategori 1\u0027","startTime":1521092456223,"endTime":0,"childRecords":[],"interuppted":false}],"interuppted":false},{"index":4,"isIgnoredIfFailed":false,"type":"TEST_STEP","name":"tap","message":"Tapped on element \u0027Object Repository/Sidebar Menu/Operasional/Pengeluaran/Pilih Kategori 1\u0027","description":"Mengklik \\\"Pilih Kategori\\\"","startTime":1521092456226,"endTime":1521092457378,"childRecords":[{"testStatus":{"stackTrace":"","statusValue":"PASSED"},"type":"MESSAGE","name":"","message":"Tapped on element \u0027Object Repository/Sidebar Menu/Operasional/Pengeluaran/Pilih Kategori 1\u0027","startTime":1521092457377,"endTime":0,"childRecords":[],"interuppted":false}],"interuppted":false},{"index":5,"isIgnoredIfFailed":false,"type":"TEST_STEP","name":"delay","message":"Delayed 3 second(s)","description":"","startTime":1521092457378,"endTime":1521092460381,"childRecords":[{"testStatus":{"stackTrace":"","statusValue":"PASSED"},"type":"MESSAGE","name":"","message":"Delayed 3 second(s)","startTime":1521092460380,"endTime":0,"childRecords":[],"interuppted":false}],"interuppted":false},{"testStatus":{"stackTrace":"","statusValue":"PASSED"},"type":"MESSAGE","name":"","message":"Test Cases/Story 41 - Create Expense/TC 3","startTime":1521092460382,"endTime":0,"childRecords":[],"interuppted":false}],"interuppted":false},{"isOptional":false,"type":"TEST_CASE","name":"Test Cases/Story 41 - Create Expense/TC 4","id":"Test Cases/Story 41 - Create Expense/TC 4","source":"C:\\\\Users\\\\AV2017005903\\\\Documents\\\\apollo-automationTest Cases\\\\Story 41 - Create Expense\\\\TC 4.tc","message":"Test Cases/Story 41 - Create Expense/TC 4","description":"Create Expense - Amount number","startTime":1521092460444,"endTime":1521092466490,"childRecords":[{"testStatus":{"stackTrace":"","statusValue":"INFO"},"type":"MESSAGE","name":"","message":"Evaluating variables for test case","startTime":1521092460446,"endTime":0,"childRecords":[],"interuppted":false},{"index":1,"isIgnoredIfFailed":false,"type":"TEST_STEP","name":"waitForElementPresent","message":"Element \u0027Object Repository/Sidebar Menu/Operasional/Pengeluaran/Pilih Kategori Elemen ke 1\u0027 is present","description":"","startTime":1521092460573,"endTime":1521092460819,"childRecords":[{"testStatus":{"stackTrace":"","statusValue":"PASSED"},"type":"MESSAGE","name":"","message":"Element \u0027Object Repository/Sidebar Menu/Operasional/Pengeluaran/Pilih Kategori Elemen ke 1\u0027 is present","startTime":1521092460818,"endTime":0,"childRecords":[],"interuppted":false}],"interuppted":false},{"index":2,"isIgnoredIfFailed":false,"type":"TEST_STEP","name":"tap","message":"Tapped on element \u0027Object Repository/Sidebar Menu/Operasional/Pengeluaran/Pilih Kategori Elemen ke 1\u0027","description":"","startTime":1521092460820,"endTime":1521092461477,"childRecords":[{"testStatus":{"stackTrace":"","statusValue":"PASSED"},"type":"MESSAGE","name":"","message":"Tapped on element \u0027Object Repository/Sidebar Menu/Operasional/Pengeluaran/Pilih Kategori Elemen ke 1\u0027","startTime":1521092461475,"endTime":0,"childRecords":[],"interuppted":false}],"interuppted":false},{"index":3,"isIgnoredIfFailed":false,"type":"TEST_STEP","name":"waitForElementPresent","message":"Element \u0027Object Repository/Sidebar Menu/Operasional/Pengeluaran/Simpan - Tambah Catatan\u0027 is present","description":"","startTime":1521092461478,"endTime":1521092463094,"childRecords":[{"testStatus":{"stackTrace":"","statusValue":"PASSED"},"type":"MESSAGE","name":"","message":"Element \u0027Object Repository/Sidebar Menu/Operasional/Pengeluaran/Simpan - Tambah Catatan\u0027 is present","startTime":1521092463092,"endTime":0,"childRecords":[],"interuppted":false}],"interuppted":false},{"index":4,"isIgnoredIfFailed":false,"type":"TEST_STEP","name":"tap","message":"Tapped on element \u0027Object Repository/Sidebar Menu/Operasional/Pengeluaran/Simpan - Tambah Catatan\u0027","description":"","startTime":1521092463094,"endTime":1521092463484,"childRecords":[{"testStatus":{"stackTrace":"","statusValue":"PASSED"},"type":"MESSAGE","name":"","message":"Tapped on element \u0027Object Repository/Sidebar Menu/Operasional/Pengeluaran/Simpan - Tambah Catatan\u0027","startTime":1521092463483,"endTime":0,"childRecords":[],"interuppted":false}],"interuppted":false},{"index":5,"isIgnoredIfFailed":false,"type":"TEST_STEP","name":"delay","message":"Delayed 3 second(s)","description":"","startTime":1521092463485,"endTime":1521092466489,"childRecords":[{"testStatus":{"stackTrace":"","statusValue":"PASSED"},"type":"MESSAGE","name":"","message":"Delayed 3 second(s)","startTime":1521092466488,"endTime":0,"childRecords":[],"interuppted":false}],"interuppted":false},{"testStatus":{"stackTrace":"","statusValue":"PASSED"},"type":"MESSAGE","name":"","message":"Test Cases/Story 41 - Create Expense/TC 4","startTime":1521092466490,"endTime":0,"childRecords":[],"interuppted":false}],"interuppted":false},{"isOptional":false,"type":"TEST_CASE","name":"Test Cases/Story 41 - Create Expense/TC 5","id":"Test Cases/Story 41 - Create Expense/TC 5","source":"C:\\\\Users\\\\AV2017005903\\\\Documents\\\\apollo-automationTest Cases\\\\Story 41 - Create Expense\\\\TC 5.tc","message":"Test Cases/Story 41 - Create Expense/TC 5","description":"Create Expense - Amount Alphabet","startTime":1521092466549,"endTime":1521092484599,"childRecords":[{"testStatus":{"stackTrace":"","statusValue":"INFO"},"type":"MESSAGE","name":"","message":"Evaluating variables for test case","startTime":1521092466565,"endTime":0,"childRecords":[],"interuppted":false},{"index":1,"isIgnoredIfFailed":false,"type":"TEST_STEP","name":"tap","message":"Tapped on element \u0027Object Repository/Sidebar Menu/Operasional/Pengeluaran/Judul Catatan - TextBox\u0027","description":"","startTime":1521092466701,"endTime":1521092467188,"childRecords":[{"testStatus":{"stackTrace":"","statusValue":"PASSED"},"type":"MESSAGE","name":"","message":"Tapped on element \u0027Object Repository/Sidebar Menu/Operasional/Pengeluaran/Judul Catatan - TextBox\u0027","startTime":1521092467186,"endTime":0,"childRecords":[],"interuppted":false}],"interuppted":false},{"index":2,"isIgnoredIfFailed":false,"type":"TEST_STEP","name":"setText","message":"Text \u0027Pengeluaran Kos Kosan\u0027 has been set to element \u0027Object Repository/Sidebar Menu/Operasional/Pengeluaran/Judul Catatan - TextBox\u0027","description":"Mengklik TextBox Judul MengInput Text pada Judul Catatan","startTime":1521092467189,"endTime":1521092482894,"childRecords":[{"testStatus":{"stackTrace":"","statusValue":"PASSED"},"type":"MESSAGE","name":"","message":"Text \u0027Pengeluaran Kos Kosan\u0027 has been set to element \u0027Object Repository/Sidebar Menu/Operasional/Pengeluaran/Judul Catatan - TextBox\u0027","startTime":1521092482891,"endTime":0,"childRecords":[],"interuppted":false}],"interuppted":false},{"index":3,"isIgnoredIfFailed":false,"type":"TEST_STEP","name":"verifyElementText","message":"Actual text and expected text of test object \u0027Object Repository/Sidebar Menu/Operasional/Pengeluaran/Judul Catatan - TextBox\u0027 are matched.","description":"","startTime":1521092482895,"endTime":1521092483786,"childRecords":[{"testStatus":{"stackTrace":"","statusValue":"PASSED"},"type":"MESSAGE","name":"","message":"Actual text and expected text of test object \u0027Object Repository/Sidebar Menu/Operasional/Pengeluaran/Judul Catatan - TextBox\u0027 are matched.","startTime":1521092483784,"endTime":0,"childRecords":[],"interuppted":false}],"interuppted":false},{"index":4,"isIgnoredIfFailed":false,"type":"TEST_STEP","name":"getText","message":"Text of element \u0027Object Repository/Sidebar Menu/Operasional/Pengeluaran/Judul Catatan - TextBox\u0027 is: \u0027Pengeluaran Kos Kosan\u0027","description":"","startTime":1521092483786,"endTime":1521092484094,"childRecords":[{"testStatus":{"stackTrace":"","statusValue":"PASSED"},"type":"MESSAGE","name":"","message":"Text of element \u0027Object Repository/Sidebar Menu/Operasional/Pengeluaran/Judul Catatan - TextBox\u0027 is: \u0027Pengeluaran Kos Kosan\u0027","startTime":1521092484092,"endTime":0,"childRecords":[],"interuppted":false}],"interuppted":false},{"index":5,"isIgnoredIfFailed":false,"type":"TEST_STEP","name":"hideKeyboard","message":"Keyboard is hidden","description":"Keyboard device tertutup","startTime":1521092484096,"endTime":1521092484599,"childRecords":[{"testStatus":{"stackTrace":"","statusValue":"PASSED"},"type":"MESSAGE","name":"","message":"Keyboard is hidden","startTime":1521092484518,"endTime":0,"childRecords":[],"interuppted":false}],"interuppted":false},{"testStatus":{"stackTrace":"","statusValue":"PASSED"},"type":"MESSAGE","name":"","message":"Test Cases/Story 41 - Create Expense/TC 5","startTime":1521092484599,"endTime":0,"childRecords":[],"interuppted":false}],"interuppted":false},{"isOptional":false,"type":"TEST_CASE","name":"Test Cases/Story 41 - Create Expense/TC 6","id":"Test Cases/Story 41 - Create Expense/TC 6","source":"C:\\\\Users\\\\AV2017005903\\\\Documents\\\\apollo-automationTest Cases\\\\Story 41 - Create Expense\\\\TC 6.tc","message":"Test Cases/Story 41 - Create Expense/TC 6","description":"Create Expense - Deskripsi","startTime":1521092484653,"endTime":1521092503688,"childRecords":[{"testStatus":{"stackTrace":"","statusValue":"INFO"},"type":"MESSAGE","name":"","message":"Evaluating variables for test case","startTime":1521092484660,"endTime":0,"childRecords":[],"interuppted":false},{"index":1,"isIgnoredIfFailed":false,"type":"TEST_STEP","name":"tap","message":"Tapped on element \u0027Object Repository/Sidebar Menu/Operasional/Pengeluaran/Nominal Pengeluaran - TextBox\u0027","description":"Mengklik \\\"Nominal Pengeluaran\\\"","startTime":1521092484779,"endTime":1521092485613,"childRecords":[{"testStatus":{"stackTrace":"","statusValue":"PASSED"},"type":"MESSAGE","name":"","message":"Tapped on element \u0027Object Repository/Sidebar Menu/Operasional/Pengeluaran/Nominal Pengeluaran - TextBox\u0027","startTime":1521092485612,"endTime":0,"childRecords":[],"interuppted":false}],"interuppted":false},{"index":2,"isIgnoredIfFailed":false,"type":"TEST_STEP","name":"setText","message":"Text \u0027Rp. 4500000\u0027 has been set to element \u0027Object Repository/Sidebar Menu/Operasional/Pengeluaran/Nominal Pengeluaran - TextBox\u0027","description":"MengInput nilai Nominal Pengeluaran","startTime":1521092485615,"endTime":1521092496984,"childRecords":[{"testStatus":{"stackTrace":"","statusValue":"PASSED"},"type":"MESSAGE","name":"","message":"Text \u0027Rp. 4500000\u0027 has been set to element \u0027Object Repository/Sidebar Menu/Operasional/Pengeluaran/Nominal Pengeluaran - TextBox\u0027","startTime":1521092496982,"endTime":0,"childRecords":[],"interuppted":false}],"interuppted":false},{"index":3,"isIgnoredIfFailed":false,"type":"TEST_STEP","name":"verifyElementText","message":"Actual text and expected text of test object \u0027Object Repository/Sidebar Menu/Operasional/Pengeluaran/Nominal Pengeluaran - TextBox\u0027 are matched.","description":"Memverifikasi nilai Nominal Pengeluaran yang telah di Input apakah sama actual dengan expectednya","startTime":1521092496986,"endTime":1521092497917,"childRecords":[{"testStatus":{"stackTrace":"","statusValue":"PASSED"},"type":"MESSAGE","name":"","message":"Actual text and expected text of test object \u0027Object Repository/Sidebar Menu/Operasional/Pengeluaran/Nominal Pengeluaran - TextBox\u0027 are matched.","startTime":1521092497916,"endTime":0,"childRecords":[],"interuppted":false}],"interuppted":false},{"index":4,"isIgnoredIfFailed":false,"type":"TEST_STEP","name":"hideKeyboard","message":"Keyboard is hidden","description":"","startTime":1521092497918,"endTime":1521092498682,"childRecords":[{"testStatus":{"stackTrace":"","statusValue":"PASSED"},"type":"MESSAGE","name":"","message":"Keyboard is hidden","startTime":1521092498523,"endTime":0,"childRecords":[],"interuppted":false}],"interuppted":false},{"index":5,"isIgnoredIfFailed":false,"type":"TEST_STEP","name":"delay","message":"Delayed 5 second(s)","description":"","startTime":1521092498683,"endTime":1521092503687,"childRecords":[{"testStatus":{"stackTrace":"","statusValue":"PASSED"},"type":"MESSAGE","name":"","message":"Delayed 5 second(s)","startTime":1521092503686,"endTime":0,"childRecords":[],"interuppted":false}],"interuppted":false},{"testStatus":{"stackTrace":"","statusValue":"PASSED"},"type":"MESSAGE","name":"","message":"Test Cases/Story 41 - Create Expense/TC 6","startTime":1521092503688,"endTime":0,"childRecords":[],"interuppted":false}],"interuppted":false},{"isOptional":false,"type":"TEST_CASE","name":"Test Cases/Story 41 - Create Expense/TC 7","id":"Test Cases/Story 41 - Create Expense/TC 7","source":"C:\\\\Users\\\\AV2017005903\\\\Documents\\\\apollo-automationTest Cases\\\\Story 41 - Create Expense\\\\TC 7.tc","message":"Test Cases/Story 41 - Create Expense/TC 7","description":"Create Expense - Tanggal Sebelum","startTime":1521092503745,"endTime":1521092517831,"childRecords":[{"testStatus":{"stackTrace":"","statusValue":"INFO"},"type":"MESSAGE","name":"","message":"Evaluating variables for test case","startTime":1521092503767,"endTime":0,"childRecords":[],"interuppted":false},{"index":1,"isIgnoredIfFailed":false,"type":"TEST_STEP","name":"waitForElementPresent","message":"Element \u0027Object Repository/Sidebar Menu/Operasional/Pengeluaran/Deskripsi - TextBox\u0027 is present","description":"Menunggu sampai nilai Nominal Pengeluaran terGet, kemudian melakukan action selanjutnya","startTime":1521092503906,"endTime":1521092504133,"childRecords":[{"testStatus":{"stackTrace":"","statusValue":"PASSED"},"type":"MESSAGE","name":"","message":"Element \u0027Object Repository/Sidebar Menu/Operasional/Pengeluaran/Deskripsi - TextBox\u0027 is present","startTime":1521092504131,"endTime":0,"childRecords":[],"interuppted":false}],"interuppted":false},{"index":2,"isIgnoredIfFailed":false,"type":"TEST_STEP","name":"tap","message":"Tapped on element \u0027Object Repository/Sidebar Menu/Operasional/Pengeluaran/Deskripsi - TextBox\u0027","description":"","startTime":1521092504133,"endTime":1521092504744,"childRecords":[{"testStatus":{"stackTrace":"","statusValue":"WARNING"},"type":"MESSAGE","name":"","message":"Timeout \u00270\u0027 is invalid. Using default page load timeout: \u002730\u0027","startTime":1521092504139,"endTime":0,"childRecords":[],"interuppted":false},{"testStatus":{"stackTrace":"","statusValue":"PASSED"},"type":"MESSAGE","name":"","message":"Tapped on element \u0027Object Repository/Sidebar Menu/Operasional/Pengeluaran/Deskripsi - TextBox\u0027","startTime":1521092504742,"endTime":0,"childRecords":[],"interuppted":false}],"interuppted":false},{"index":3,"isIgnoredIfFailed":false,"type":"TEST_STEP","name":"sendKeys","message":"Send keys \u0027Pengeluaran untuk uang Listrik, Uang Makan, dan Uang Kos bulan Januari\u0027 on test object \u0027Object Repository/Sidebar Menu/Operasional/Pengeluaran/Deskripsi - TextBox\u0027 successfully.","description":"Mengklik TextBox Deskripsi dan mengInput Deskripsinya ","startTime":1521092504745,"endTime":1521092514263,"childRecords":[{"testStatus":{"stackTrace":"","statusValue":"PASSED"},"type":"MESSAGE","name":"","message":"Send keys \u0027Pengeluaran untuk uang Listrik, Uang Makan, dan Uang Kos bulan Januari\u0027 on test object \u0027Object Repository/Sidebar Menu/Operasional/Pengeluaran/Deskripsi - TextBox\u0027 successfully.","startTime":1521092514260,"endTime":0,"childRecords":[],"interuppted":false}],"interuppted":false},{"index":4,"isIgnoredIfFailed":false,"type":"TEST_STEP","name":"getText","message":"Text of element \u0027Object Repository/Sidebar Menu/Operasional/Pengeluaran/Deskripsi - TextBox\u0027 is: \u0027Pengeluaran untuk uang Listrik, Uang Makan, dan Uang Kos bulan Januari\u0027","description":"Mengambil nilai Nominal Pengeluaran setelah di verifikasi","startTime":1521092514265,"endTime":1521092515209,"childRecords":[{"testStatus":{"stackTrace":"","statusValue":"PASSED"},"type":"MESSAGE","name":"","message":"Text of element \u0027Object Repository/Sidebar Menu/Operasional/Pengeluaran/Deskripsi - TextBox\u0027 is: \u0027Pengeluaran untuk uang Listrik, Uang Makan, dan Uang Kos bulan Januari\u0027","startTime":1521092515207,"endTime":0,"childRecords":[],"interuppted":false}],"interuppted":false},{"index":5,"isIgnoredIfFailed":false,"type":"TEST_STEP","name":"hideKeyboard","message":"Keyboard is hidden","description":"Keyboard device tertutup","startTime":1521092515209,"endTime":1521092515826,"childRecords":[{"testStatus":{"stackTrace":"","statusValue":"PASSED"},"type":"MESSAGE","name":"","message":"Keyboard is hidden","startTime":1521092515675,"endTime":0,"childRecords":[],"interuppted":false}],"interuppted":false},{"index":6,"isIgnoredIfFailed":false,"type":"TEST_STEP","name":"delay","message":"Delayed 2 second(s)","description":"","startTime":1521092515827,"endTime":1521092517830,"childRecords":[{"testStatus":{"stackTrace":"","statusValue":"PASSED"},"type":"MESSAGE","name":"","message":"Delayed 2 second(s)","startTime":1521092517829,"endTime":0,"childRecords":[],"interuppted":false}],"interuppted":false},{"testStatus":{"stackTrace":"","statusValue":"PASSED"},"type":"MESSAGE","name":"","message":"Test Cases/Story 41 - Create Expense/TC 7","startTime":1521092517831,"endTime":0,"childRecords":[],"interuppted":false}],"interuppted":false},{"isOptional":false,"type":"TEST_CASE","name":"Test Cases/Story 41 - Create Expense/TC 8","id":"Test Cases/Story 41 - Create Expense/TC 8","source":"C:\\\\Users\\\\AV2017005903\\\\Documents\\\\apollo-automationTest Cases\\\\Story 41 - Create Expense\\\\TC 8.tc","message":"Test Cases/Story 41 - Create Expense/TC 8 FAILED because (of) Failed to tap on element \u0027Object Repository/Sidebar Menu/Operasional/Pengeluaran/10 Maret 2018\u0027 (Root cause: Object Object Repository/Sidebar Menu/Operasional/Pengeluaran/10 Maret 2018 not found)","description":"Create Expense - Tanggal Sesudah","startTime":1521092517885,"endTime":1521092525051,"childRecords":[{"testStatus":{"stackTrace":"","statusValue":"INFO"},"type":"MESSAGE","name":"","message":"Evaluating variables for test case","startTime":1521092517902,"endTime":0,"childRecords":[],"interuppted":false},{"index":1,"isIgnoredIfFailed":false,"type":"TEST_STEP","name":"waitForElementPresent","message":"Element \u0027Object Repository/Sidebar Menu/Operasional/Pengeluaran/SelectorTangal\u0027 is present","description":"Menunggu sampai Deskripsi selesai di Input, kemudian melakukan action selanjutnya","startTime":1521092518018,"endTime":1521092518309,"childRecords":[{"testStatus":{"stackTrace":"","statusValue":"PASSED"},"type":"MESSAGE","name":"","message":"Element \u0027Object Repository/Sidebar Menu/Operasional/Pengeluaran/SelectorTangal\u0027 is present","startTime":1521092518309,"endTime":0,"childRecords":[],"interuppted":false}],"interuppted":false},{"index":2,"isIgnoredIfFailed":false,"type":"TEST_STEP","name":"tap","message":"Tapped on element \u0027Object Repository/Sidebar Menu/Operasional/Pengeluaran/SelectorTangal\u0027","description":"Mengklik Selector Tanggal Pengeluaran","startTime":1521092518309,"endTime":1521092518738,"childRecords":[{"testStatus":{"stackTrace":"","statusValue":"PASSED"},"type":"MESSAGE","name":"","message":"Tapped on element \u0027Object Repository/Sidebar Menu/Operasional/Pengeluaran/SelectorTangal\u0027","startTime":1521092518737,"endTime":0,"childRecords":[],"interuppted":false}],"interuppted":false},{"index":3,"isIgnoredIfFailed":false,"type":"TEST_STEP","name":"waitForElementPresent","message":"Object Object Repository/Sidebar Menu/Operasional/Pengeluaran/10 Maret 2018 not found","description":"","startTime":1521092518738,"endTime":1521092522936,"childRecords":[{"testStatus":{"stackTrace":"","statusValue":"WARNING"},"type":"MESSAGE","name":"","message":"Object Object Repository/Sidebar Menu/Operasional/Pengeluaran/10 Maret 2018 not found","startTime":1521092522934,"endTime":0,"childRecords":[],"interuppted":false}],"interuppted":false},{"index":4,"isIgnoredIfFailed":false,"type":"TEST_STEP","name":"tap","message":"Failed to tap on element \u0027Object Repository/Sidebar Menu/Operasional/Pengeluaran/10 Maret 2018\u0027 (Root cause: Object Object Repository/Sidebar Menu/Operasional/Pengeluaran/10 Maret 2018 not found)","description":"","startTime":1521092522936,"endTime":1521092525047,"childRecords":[{"testStatus":{"stackTrace":"","statusValue":"FAILED"},"type":"MESSAGE","name":"","message":"Object Object Repository/Sidebar Menu/Operasional/Pengeluaran/10 Maret 2018 not found","startTime":1521092525045,"endTime":0,"childRecords":[],"interuppted":false},{"testStatus":{"stackTrace":"","statusValue":"FAILED"},"type":"MESSAGE","name":"","message":"Failed to tap on element \u0027Object Repository/Sidebar Menu/Operasional/Pengeluaran/10 Maret 2018\u0027 (Root cause: Object Object Repository/Sidebar Menu/Operasional/Pengeluaran/10 Maret 2018 not found)","startTime":1521092525047,"endTime":0,"childRecords":[],"interuppted":false}],"interuppted":false},{"testStatus":{"stackTrace":"","statusValue":"FAILED"},"type":"MESSAGE","name":"","message":"Test Cases/Story 41 - Create Expense/TC 8 FAILED because (of) Failed to tap on element \u0027Object Repository/Sidebar Menu/Operasional/Pengeluaran/10 Maret 2018\u0027 (Root cause: Object Object Repository/Sidebar Menu/Operasional/Pengeluaran/10 Maret 2018 not found)","startTime":1521092525047,"endTime":0,"childRecords":[],"interuppted":false}],"interuppted":false},{"isOptional":false,"type":"TEST_CASE","name":"Test Cases/Story 41 - Create Expense/TC 9","id":"Test Cases/Story 41 - Create Expense/TC 9","source":"C:\\\\Users\\\\AV2017005903\\\\Documents\\\\apollo-automationTest Cases\\\\Story 41 - Create Expense\\\\TC 9.tc","message":"Test Cases/Story 41 - Create Expense/TC 9 FAILED because (of) Failed to tap on element \u0027Object Repository/Sidebar Menu/Operasional/Pengeluaran/SelectorTangal\u0027 (Root cause: Object Object Repository/Sidebar Menu/Operasional/Pengeluaran/SelectorTangal not found)","description":"Create Expense - Sudah dibayar Checklist","startTime":1521092525103,"endTime":1521092531406,"childRecords":[{"testStatus":{"stackTrace":"","statusValue":"INFO"},"type":"MESSAGE","name":"","message":"Evaluating variables for test case","startTime":1521092525109,"endTime":0,"childRecords":[],"interuppted":false},{"index":1,"isIgnoredIfFailed":false,"type":"TEST_STEP","name":"waitForElementPresent","message":"Element \u0027Object Repository/Sidebar Menu/Operasional/Pengeluaran/SelectorTangal\u0027 is present","description":"Menunggu sampai Deskripsi selesai di Input, kemudian melakukan action selanjutnya","startTime":1521092525210,"endTime":1521092525556,"childRecords":[{"testStatus":{"stackTrace":"","statusValue":"PASSED"},"type":"MESSAGE","name":"","message":"Element \u0027Object Repository/Sidebar Menu/Operasional/Pengeluaran/SelectorTangal\u0027 is present","startTime":1521092525555,"endTime":0,"childRecords":[],"interuppted":false}],"interuppted":false},{"index":2,"isIgnoredIfFailed":false,"type":"TEST_STEP","name":"tap","message":"Tapped on element \u0027Object Repository/Sidebar Menu/Operasional/Pengeluaran/SelectorTangal\u0027","description":"Mengklik Selector Tanggal Pengeluaran","startTime":1521092525557,"endTime":1521092526192,"childRecords":[{"testStatus":{"stackTrace":"","statusValue":"PASSED"},"type":"MESSAGE","name":"","message":"Tapped on element \u0027Object Repository/Sidebar Menu/Operasional/Pengeluaran/SelectorTangal\u0027","startTime":1521092526190,"endTime":0,"childRecords":[],"interuppted":false}],"interuppted":false},{"index":3,"isIgnoredIfFailed":false,"type":"TEST_STEP","name":"tap","message":"Failed to tap on element \u0027Object Repository/Sidebar Menu/Operasional/Pengeluaran/SelectorTangal\u0027 (Root cause: Object Object Repository/Sidebar Menu/Operasional/Pengeluaran/SelectorTangal not found)","description":"Mengklik Selector Tanggal Pengeluaran","startTime":1521092526192,"endTime":1521092531406,"childRecords":[{"testStatus":{"stackTrace":"","statusValue":"FAILED"},"type":"MESSAGE","name":"","message":"Object Object Repository/Sidebar Menu/Operasional/Pengeluaran/SelectorTangal not found","startTime":1521092531401,"endTime":0,"childRecords":[],"interuppted":false},{"testStatus":{"stackTrace":"","statusValue":"FAILED"},"type":"MESSAGE","name":"","message":"Failed to tap on element \u0027Object Repository/Sidebar Menu/Operasional/Pengeluaran/SelectorTangal\u0027 (Root cause: Object Object Repository/Sidebar Menu/Operasional/Pengeluaran/SelectorTangal not found)","startTime":1521092531404,"endTime":0,"childRecords":[],"interuppted":false}],"interuppted":false},{"testStatus":{"stackTrace":"","statusValue":"FAILED"},"type":"MESSAGE","name":"","message":"Test Cases/Story 41 - Create Expense/TC 9 FAILED because (of) Failed to tap on element \u0027Object Repository/Sidebar Menu/Operasional/Pengeluaran/SelectorTangal\u0027 (Root cause: Object Object Repository/Sidebar Menu/Operasional/Pengeluaran/SelectorTangal not found)","startTime":1521092531406,"endTime":0,"childRecords":[],"interuppted":false}],"interuppted":false},{"isOptional":false,"type":"TEST_CASE","name":"Test Cases/Story 41 - Create Expense/TC 10","id":"Test Cases/Story 41 - Create Expense/TC 10","source":"C:\\\\Users\\\\AV2017005903\\\\Documents\\\\apollo-automationTest Cases\\\\Story 41 - Create Expense\\\\TC 10.tc","message":"Test Cases/Story 41 - Create Expense/TC 10 FAILED because (of) Failed to tap on element \u0027Object Repository/Sidebar Menu/Operasional/Pengeluaran/Batal\u0027 (Root cause: Object Object Repository/Sidebar Menu/Operasional/Pengeluaran/Batal not found)","description":"Create Expense - Simpan","startTime":1521092531460,"endTime":1521092544076,"childRecords":[{"testStatus":{"stackTrace":"","statusValue":"INFO"},"type":"MESSAGE","name":"","message":"Evaluating variables for test case","startTime":1521092531461,"endTime":0,"childRecords":[],"interuppted":false},{"index":1,"isIgnoredIfFailed":false,"type":"TEST_STEP","name":"delay","message":"Delayed 5 second(s)","description":"","startTime":1521092531577,"endTime":1521092536583,"childRecords":[{"testStatus":{"stackTrace":"","statusValue":"PASSED"},"type":"MESSAGE","name":"","message":"Delayed 5 second(s)","startTime":1521092536581,"endTime":0,"childRecords":[],"interuppted":false}],"interuppted":false},{"index":2,"isIgnoredIfFailed":false,"type":"TEST_STEP","name":"pressBack","message":"Press back button successfully","description":"","startTime":1521092536584,"endTime":1521092536993,"childRecords":[{"testStatus":{"stackTrace":"","statusValue":"PASSED"},"type":"MESSAGE","name":"","message":"Press back button successfully","startTime":1521092536993,"endTime":0,"childRecords":[],"interuppted":false}],"interuppted":false},{"index":3,"isIgnoredIfFailed":false,"type":"TEST_STEP","name":"waitForElementPresent","message":"Object Object Repository/Sidebar Menu/Operasional/Pengeluaran/Batal not found","description":"","startTime":1521092536994,"endTime":1521092541019,"childRecords":[{"testStatus":{"stackTrace":"","statusValue":"WARNING"},"type":"MESSAGE","name":"","message":"Object Object Repository/Sidebar Menu/Operasional/Pengeluaran/Batal not found","startTime":1521092541017,"endTime":0,"childRecords":[],"interuppted":false}],"interuppted":false},{"index":4,"isIgnoredIfFailed":false,"type":"TEST_STEP","name":"tap","message":"Failed to tap on element \u0027Object Repository/Sidebar Menu/Operasional/Pengeluaran/Batal\u0027 (Root cause: Object Object Repository/Sidebar Menu/Operasional/Pengeluaran/Batal not found)","description":"","startTime":1521092541020,"endTime":1521092544076,"childRecords":[{"testStatus":{"stackTrace":"","statusValue":"FAILED"},"type":"MESSAGE","name":"","message":"Object Object Repository/Sidebar Menu/Operasional/Pengeluaran/Batal not found","startTime":1521092544073,"endTime":0,"childRecords":[],"interuppted":false},{"testStatus":{"stackTrace":"","statusValue":"FAILED"},"type":"MESSAGE","name":"","message":"Failed to tap on element \u0027Object Repository/Sidebar Menu/Operasional/Pengeluaran/Batal\u0027 (Root cause: Object Object Repository/Sidebar Menu/Operasional/Pengeluaran/Batal not found)","startTime":1521092544074,"endTime":0,"childRecords":[],"interuppted":false}],"interuppted":false},{"testStatus":{"stackTrace":"","statusValue":"FAILED"},"type":"MESSAGE","name":"","message":"Test Cases/Story 41 - Create Expense/TC 10 FAILED because (of) Failed to tap on element \u0027Object Repository/Sidebar Menu/Operasional/Pengeluaran/Batal\u0027 (Root cause: Object Object Repository/Sidebar Menu/Operasional/Pengeluaran/Batal not found)","startTime":1521092544076,"endTime":0,"childRecords":[],"interuppted":false}],"interuppted":false},{"isOptional":false,"type":"TEST_CASE","name":"Test Cases/Story 41 - Create Expense/TC 11","id":"Test Cases/Story 41 - Create Expense/TC 11","source":"C:\\\\Users\\\\AV2017005903\\\\Documents\\\\apollo-automationTest Cases\\\\Story 41 - Create Expense\\\\TC 11.tc","message":"Test Cases/Story 41 - Create Expense/TC 11","description":"Create Expense - Simpan blank","startTime":1521092544132,"endTime":1521092552887,"childRecords":[{"testStatus":{"stackTrace":"","statusValue":"INFO"},"type":"MESSAGE","name":"","message":"Evaluating variables for test case","startTime":1521092544134,"endTime":0,"childRecords":[],"interuppted":false},{"index":1,"isIgnoredIfFailed":false,"type":"TEST_STEP","name":"waitForElementPresent","message":"Element \u0027Object Repository/Sidebar Menu/Operasional/Pengeluaran/Simpan - Tambah Catatan\u0027 is present","description":"","startTime":1521092544249,"endTime":1521092544574,"childRecords":[{"testStatus":{"stackTrace":"","statusValue":"PASSED"},"type":"MESSAGE","name":"","message":"Element \u0027Object Repository/Sidebar Menu/Operasional/Pengeluaran/Simpan - Tambah Catatan\u0027 is present","startTime":1521092544574,"endTime":0,"childRecords":[],"interuppted":false}],"interuppted":false},{"index":2,"isIgnoredIfFailed":false,"type":"TEST_STEP","name":"tap","message":"Tapped on element \u0027Object Repository/Sidebar Menu/Operasional/Pengeluaran/Simpan - Tambah Catatan\u0027","description":"Mengklik Button \\\"Simpan\\\" untuk  menyimpan Catatan ","startTime":1521092544574,"endTime":1521092544957,"childRecords":[{"testStatus":{"stackTrace":"","statusValue":"PASSED"},"type":"MESSAGE","name":"","message":"Tapped on element \u0027Object Repository/Sidebar Menu/Operasional/Pengeluaran/Simpan - Tambah Catatan\u0027","startTime":1521092544957,"endTime":0,"childRecords":[],"interuppted":false}],"interuppted":false},{"index":3,"isIgnoredIfFailed":false,"type":"TEST_STEP","name":"delay","message":"Delayed 5 second(s)","description":"","startTime":1521092544957,"endTime":1521092549960,"childRecords":[{"testStatus":{"stackTrace":"","statusValue":"PASSED"},"type":"MESSAGE","name":"","message":"Delayed 5 second(s)","startTime":1521092549958,"endTime":0,"childRecords":[],"interuppted":false}],"interuppted":false},{"index":4,"isIgnoredIfFailed":false,"type":"TEST_STEP","name":"comment","message":"End Story 41","description":"","startTime":1521092549961,"endTime":1521092549961,"childRecords":[],"interuppted":false},{"index":5,"isIgnoredIfFailed":false,"type":"TEST_STEP","name":"closeApplication","message":"Close app successfully","description":"","startTime":1521092549961,"endTime":1521092552886,"childRecords":[{"testStatus":{"stackTrace":"","statusValue":"PASSED"},"type":"MESSAGE","name":"","message":"Close app successfully","startTime":1521092552886,"endTime":0,"childRecords":[],"interuppted":false}],"interuppted":false},{"testStatus":{"stackTrace":"","statusValue":"PASSED"},"type":"MESSAGE","name":"","message":"Test Cases/Story 41 - Create Expense/TC 11","startTime":1521092552886,"endTime":0,"childRecords":[],"interuppted":false}],"interuppted":false}],"interuppted":false}